fsoft_diff_patch/__init__.py
fsoft_diff_patch-0.1.1.dist-info/METADATA
fsoft_diff_patch-0.1.1.dist-info/WHEEL
fsoft_diff_patch-0.1.1.dist-info/top_level.txt
fsoft_diff_patch-0.1.1.dist-info/RECORD
